discord_serverless.py
discord_serverless-2023.1005a0.dist-info/LICENSE.md
discord_serverless-2023.1005a0.dist-info/METADATA
discord_serverless-2023.1005a0.dist-info/WHEEL
discord_serverless-2023.1005a0.dist-info/top_level.txt
discord_serverless-2023.1005a0.dist-info/RECORD
