Metadata-Version: 2.1
Name: discord-serverless
Version: 2023.1005a0
Summary: Simplified serverless Discord bot interactions
Author-email: Ross Bamford <roscopeco@gmail.com>
License: Copyright 2023 Ross Bamford & Contributors
Project-URL: Homepage, https://github.com/roscopeco/discord-serverless
Keywords: feed,reader,tutorial
Classifier: License :: OSI Approved :: MIT License
Classifier: Programming Language :: Python
Classifier: Programming Language :: Python :: 3
Requires-Python: >=3.10
License-File: LICENSE.md
Requires-Dist: pynacl (>=1.5.0)
Requires-Dist: requests (>=2.31.0)
Provides-Extra: dev
Requires-Dist: black ; extra == 'dev'
Requires-Dist: bumpver ; extra == 'dev'
Requires-Dist: pre-commit ; extra == 'dev'
Requires-Dist: isort ; extra == 'dev'
Requires-Dist: pip-tools ; extra == 'dev'
Requires-Dist: pytest ; extra == 'dev'
